HttpxLibrary/HttpxKeywords.py
HttpxLibrary/HttpxOnSessionKeywords.py
HttpxLibrary/RetryKeywords.py
HttpxLibrary/SessionKeywords.py
HttpxLibrary/__init__.py
HttpxLibrary/compat.py
HttpxLibrary/exceptions.py
HttpxLibrary/log.py
HttpxLibrary/utils.py
HttpxLibrary/version.py
robotframework_httpx-0.4.8.dist-info/licenses/LICENSE.md
robotframework_httpx-0.4.8.dist-info/METADATA
robotframework_httpx-0.4.8.dist-info/WHEEL
robotframework_httpx-0.4.8.dist-info/top_level.txt
robotframework_httpx-0.4.8.dist-info/RECORD
